{
  "id": "fixture-imessage-identity-001",
  "source": "imessage",
  "channel": "imessage",
  "thread_id": "imessage:+18313452220",
  "reference_time": "2025-04-18T15:00:00Z",
  "events": [
    {
      "id": "imessage:7C6594DE-1F81-498C-B3D6-8FE4E2A72250",
      "timestamp": "2025-04-18T14:56:22Z",
      "sender": "Tyler",
      "sender_identifier": "+17072876731",
      "content": "Tnapathy@gmail.com is my personal email",
      "direction": "outbound"
    },
    {
      "id": "imessage:EAA951E4-ABAC-456B-ABED-F956BA5713B3",
      "timestamp": "2025-04-18T14:58:18Z",
      "sender": "Joe Schooler",
      "sender_identifier": "+18313452220",
      "content": "Thanks man! Ill send you an email with some prds on the concepts, no need for a NDA!",
      "direction": "inbound"
    }
  ],
  "metadata": {
    "description": "Tyler self-discloses his personal email to Joe Schooler",
    "coverage_tags": ["identity_disclosure", "email", "self_disclosed", "imessage"],
    "notes": "Tests: entity extraction (2 people), identity promotion (email → alias), source_type=self_disclosed"
  }
}
